{
 "type": "A",
 "title": "switch",
 "h1": "<code class=\"language-javascript\">switch</code>",
 "description": "Contenido de la lección «switch».",
 "printDescription": "Página para imprimir de la lección «switch».",
 "listado": [
  {
   "name": "mAswitch.html",
   "title": "La estructura de control switch",
   "h1": "La estructura de control <dfn><code class=\"language-javascript\">switch</code></dfn>",
   "description": "Definición de la estructura de control switch."
  },
  {
   "name": "mBswitchEj.html",
   "title": "Ejemplo de switch",
   "h1": "Ejemplo de <code class=\"language-javascript\">switch</code>",
   "description": "Ejemplo de switch."
  },
  {
   "name": "mCswitchDefault.html",
   "title": "La estructura de control switch-default",
   "h1": "La estructura de control <dfn><code class=\"language-javascript\">switch-default</code></dfn>",
   "description": "Definición de la estructura de control switch-default."
  },
  {
   "name": "mDswitchDefaultEj.html",
   "title": "Ejemplo de switch-default",
   "h1": "Ejemplo de <code class=\"language-javascript\">switch-default</code>",
   "description": "Ejemplo de switch-default."
  },
  {
   "name": "mEresumen.html",
   "title": "Resumen",
   "description": "Resumen de la lección «switch»."
  }
 ]
}